src/__init__.py
src/cft.py
src/main.cpp
cft-1.0.17.dist-info/METADATA
cft-1.0.17.dist-info/WHEEL
cft-1.0.17.dist-info/entry_points.txt
cft-1.0.17.dist-info/top_level.txt
cft-1.0.17.dist-info/RECORD
