Metadata-Version: 2.1
Name: cft
Version: 1.0.17
Summary: codeforces command line tool
Home-page: UNKNOWN
Author: granddaifuku
Author-email: grandnadaifuku@gmail.com
License: MIT
Platform: any
